{"title":"다음 연예 ─ 뉴스 ─ 영화","url":"https://entertain.daum.net/news/movie","favicon":"https://entertain.daum.net/news/favicon.ico","elements":[{"title":"‘거미집’ 김지운, 최우수감독상..'올빼미' 4관왕·'밀수' 3관왕","contents":"[OSEN=김채연 기자] 제28회 춘사영화제 최우수감독상은 ‘거미집’ 김지운 감독에 돌아갔다. 7일 오후 서울 강남구 건설회관 비스타홀에서 제28회 춘사국제영화제가 배우 송지우, 이규한, 개그맨 이병진의 사회로 진행됐다. 올해로 28회째를 맞이한 한국영화감독협회가 주최 및 주관하는 춘사국제영화제는 한국 영화계에 큰 획은 그은 춘사(春史) 나운규의 정신을","link":"https://v.daum.net/v/20231207220020095","retrieved":1701954854813},{"title":"춘사영화제, 함께 웃은 '거미집'·'올빼미'·'밀수'…최우수감독상은 김지운","contents":"'거미집' '올빼미' '밀수'가 '제28회 춘사국제영화제'에서 수상의 기쁨을 함께 누렸다. 최우수감독상의 영광은 '거미집'을 연출한 김지운이 차지하게 됐다. 7일 서울 강남구 논현동 건설회관에서는 '제28회 춘사국제영화제'가 진행됐다. '춘사국제영화제'는 춘사(春史) 나운규의 영화를 향한 열정, 삶에 대한 투혼을 기리고자 개최되고 있다. 한국영화감독협회가","link":"https://v.daum.net/v/20231207215445995","retrieved":1701954854817},{"title":"'여우주연상' 김혜수 \"염정아와 사랑에 빠지고, 조인성에 배워\"…'거미집' 최우수감독상","contents":"[마이데일리 = 박서연 기자] 영화 '거미집' 김지운 감독이 최우수감독상을, 배우 김혜수가 '밀수'로 여우주연상의 영예를 안았다.  7일 오후 서울 강남구 건설회관 비스타홀에서 제28회 춘사국제영화제가 개최된 가운데, 온라인을 통해 생중계 됐다. 진행은 배우 이규한, 송지우, 개그맨 이병진이 맡았다. 이날 '거미집'의 김지운 감독은 최우수감독상을 품에","link":"https://v.daum.net/v/20231207210143253","retrieved":1701951331323},{"title":"'올빼미' 류준열·'밀수' 김혜수, 남녀주연상 수상..“진심으로 영광”","contents":"[OSEN=김채연 기자] 배우 류준열과 김혜수가 ‘제28회 춘사국제영화제’ 남녀주연상의 기쁨을 나눴다. 7일 오후 서울 강남구 건설회관 비스타홀에서 제28회 춘사국제영화제가 배우 송지우, 이규한, 개그맨 이병진의 사회로 진행됐다. 올해로 28회째를 맞이한 한국영화감독협회가 주최 및 주관하는 춘사국제영화제는 한국 영화계에 큰 획은 그은 춘사(春史) 나운규","link":"https://v.daum.net/v/20231207205620165","retrieved":1701951331324},{"title":"정수정, ‘거미집’으로 첫 영화제 조연상..“상복 없다고 생각했는데”","contents":"[OSEN=김채연 기자] 배우 정수정(크리스탈)이 ‘거미집’으로 첫 영화제 조연상을 수상했다. 7일 오후 서울 강남구 건설회관 비스타홀에서 제28회 춘사국제영화제가 배우 송지우, 이규한, 개그맨 이병진의 사회로 진행됐다. 올해로 28회째를 맞이한 한국영화감독협회가 주최 및 주관하는 춘사국제영화제는 한국 영화계에 큰 획은 그은 춘사(春史) 나운규의 정신을","link":"https://v.daum.net/v/20231207202627683","retrieved":1701951331325},{"title":"'거미집' 정수정, 여우조연상 \"큰 상 받을 복 없다 생각했는데…\"","contents":"[마이데일리 = 박서연 기자] 배우 정수정이 여우조연상의 영광을 누렸다.  7일 오후 서울 강남구 건설회관 비스타홀에서 '제28회 춘사국제영화제'가 개최된 가운데, 온라인을 통해 생중계 됐다. 진행은 배우 이규한, 송지우, 개그맨 이병진이 맡았다. 이날 여우조연상은 '거미집'의 정수정이 수상했다. 정수정은 \"제가 영광스럽고 큰 상을 받을 복이 없다","link":"https://v.daum.net/v/20231207202541668","retrieved":1701951331328},{"title":"김성철, '올빼미'로 신인남우상 수상..\"좋은 연기로 보답할 것\"","contents":"[스타뉴스 | 이승훈 기자] 배우 김성철이 7일 오후 서울 강남구 건설회관에서 진행된 제28회 춘사국제영화제 레드카펫 행사에 참석해 포즈를 취하고 있다. /2023.12.07 /사진=이동훈배우 김성철이 '28회 춘사국제영화제' 신인남우상을 품에 안았다. 7일 오후 서울 강남구 소재 건설회관 비스타홀에서 제28회 춘사국제영화제가 진행됐다. 이날 영화","link":"https://v.daum.net/v/20231207202302626","retrieved":1701951331329},{"title":"부산영화제 혁신안 나왔지만...'임추위' 과도한 역할 논란","contents":"[성하훈 기자] ▲ &nbsp;28회 부산국제영화제 폐막식ⓒ 부산영화제 제공&nbsp; 부산영화제 혁신위원회가 6일 오후 부산영상산업센터에서 부산시민과 언론대상 간담회를 통해 구체적인 방향을 발표했다. 지난 6월 말 이용관 이사장 사퇴 선언 이후 구성된 혁신위원회는 정관 개정에 대한 방안을 논의해 왔다. 12월 말 활동시한 종료를 앞두고 구체적 방안을 공개한 것이다. 혁신위","link":"https://v.daum.net/v/20231207201800530","retrieved":1701951331330},{"title":"김성철, 신인남우상 수상 \"'올빼미' 축하 많이 해줬는데…상은 처음\"","contents":"[마이데일리 = 박서연 기자] 배우 김성철, 고민시가 '제28회 춘사국제영화제' 신인남우·여우주연상을 받았다.  7일 오후 서울 강남구 건설회관 비스타홀에서 '제28회 춘사국제영화제'가 개최된 가운데, 온라인을 통해 생중계 됐다. 진행은 배우 이규한, 송지우, 개그맨 이병진이 맡았다. 신인남우상은 '올빼미'의 김성철이 수상했다. 김성철은 \"올해 많은","link":"https://v.daum.net/v/20231207201746527","retrieved":1701951331331},{"title":"‘올빼미’ 김성철·‘밀수’ 고민시, 남녀신인상..“좋은 연기로 보답할 것”","contents":"[OSEN=김채연 기자] 인생에서 단 한번 뿐인 신인상은 ‘올빼미’ 김성철과 ‘밀수’ 고민시에게 돌아갔다. 7일 오후 서울 강남구 건설회관 비스타홀에서 제28회 춘사국제영화제가 배우 송지우, 이규한, 개그맨 이병진의 사회로 진행됐다. 먼저 신인남우상은 김성철, 서인국, 윤시윤이 후보에 오른 가운데 ‘올빼미’의 김성철이 수상의 영광을 안았다. 김성철은 “","link":"https://v.daum.net/v/20231207201658516","retrieved":1701951331333},{"title":"\"내가 가장 원망스럽다\"…'서울의 봄' 정우성 모티브 인물의 끝","contents":"(엑스포츠뉴스 오승현 기자) '서울의 봄' 속 주인공 이태신의 모티브가 된 실존 인물의 솔직한 마음은 어땠을까. 최근 개봉한 영화 '서울의 봄'(감독 김성수)은 1979년 12월 12일 수도 서울에서 일어난 신군부 세력의 반란을 막기 위한 일촉즉발의 9시간을 그린 영화다. 실제 있던 일인 12·12 사태를 배경으로 한 이 영화는 대중의 뜨거운 지지를 받으며","link":"https://v.daum.net/v/20231207193002714","retrieved":1701947083299},{"title":"사랑에 빠진 나폴레옹의 재해석, 호불호 갈린 까닭","contents":"[원종빈 기자] * 이 글에는 영화의 스포일러가 있습니다.&nbsp; 1793년, 프랑스의 왕후 마리 앙투아네트가 단두대에서 처형당한다. 흥분과 광기에 휩싸인 군중 사이에서 이 광경을 지켜보는 코르시카 출신의 포병 장교 '나폴레옹'(호아킨 피닉스). 그는 이 혼란을 자기 기회로 삼기로 결정하고, 툴룽에서 영국군을 무찌르며 영웅으로 떠오르기 시작한다.&nbsp; 때마침 하늘도","link":"https://v.daum.net/v/20231207190001159","retrieved":1701947083300},{"title":"총성과 포격‥‘서울의 봄’ 혼란스러웠던 1979년 그날 어떻게 재현했나","contents":"[뉴스엔 배효주 기자] 500만 관객을 돌파한 '서울의 봄'이 1979년 그날을 완벽 재현해 호평을 받고 있다. 영화 '서울의 봄'(감독 김성수)은 1979년 12월 12일 수도 서울에서 일어난 신군부 세력의 반란을 막기 위한 일촉즉발의 9시간을 그린 영화다. VFX콘텐츠 제작 전문기업 덱스터스튜디오가 DI(디지털 색보정) 기술을 맡았으며, 자회사 라이브","link":"https://v.daum.net/v/20231207184659903","retrieved":1701947083301},{"title":"\"도와달라\"…'시민덕희' 안은진, 충무로 블루칩 될까","contents":"[OSEN=김보라 기자]&nbsp;드라마 ‘연인’(2023)을 통해 인지도를 높이고 인기를 얻게 된 배우 안은진이 영화 ‘시민덕희’를 발판삼아 충무로 블루칩이 될 수 있을지 주목된다. 지난해 11월 개봉한 영화 ‘올빼미’(감독 안태진)에서 소용조씨 역을 맡아 관객들을 만났던 안은진은 촬영 시기상 “‘시민덕희’가 첫 영화”라고 한다. ‘시민덕희’의 극장 개봉이 2","link":"https://v.daum.net/v/20231207182717399","retrieved":1701947083302},{"title":"‘서울의 봄’ 다음은 ‘노량’ 올겨울은 역사물이 흥한다","contents":"[뉴스엔 배효주 기자] '서울의 봄'의 흥행세를 이어 '노량: 죽음의 바다'가 역사의 힘으로 연말 극장가를 사로잡을 전망이다. 500만 관객을 돌파한 영화 '서울의 봄'(감독 김성수)은 1979년 12월 12일, 수도 서울에서 일어난 신군부 세력의 반란을 막기 위한 일촉즉발의 9시간을 그린 작품이다. 영화를 통해 군사반란을 경험해보지 못한 관람객들에게는","link":"https://v.daum.net/v/20231207174418038","retrieved":1701939865226}]}