{"title":"다음 연예 ─ 뉴스 ─ 영화","url":"https://entertain.daum.net/news/movie","favicon":"https://entertain.daum.net/news/favicon.ico","elements":[{"title":"'올빼미' 류쥰열 \"유해진과 비슷한 그림체인데 왜 나에겐 잘생겼다 하지 않나? 서운해\"","contents":"영화 '올빼미'에서 세자의 죽음을 목격한 맹인 침술사 '경수'를 통해 배우로서 또 한번 연기 스펙트럼을 넓힌 류준열을 만났다. 극 중에서 '경수'는 뛰어난 침술 실력을 인정받은 맹인 침술사이지만 사실은 낮에는 앞이 보이지 않지만 빛이 없는 어두운 상황에서는 사물이 보이는 주맹증을 앓고 있는 인물로, 우연히 '소현세지'의 죽음을 목격하며 진실을 밝히기 위해","link":"https://v.daum.net/v/20221203230150165","retrieved":1670076324040},{"title":"‘트랜스포머: 비스트의 서막’ 2023년 6월 개봉 확정","contents":"[동아닷컴] ‘트랜스포머: 비스트의 서막’ 2023년 6월 개봉 확정 [공식] 영화 ‘트랜스포머: 비스트의 서막’이 2023년 6월 개봉을 확정했다. 2007년부터 역사를 써온 ‘트랜스포머’가 2023년 완벽히 새롭고 강력해진 신작 ‘트랜스포머: 비스트의 서막’으로 돌아온다. ‘트랜스포머’는 현재까지 다섯 편의 ‘트랜스포머’ 시리즈, 그리고 인기 캐릭터","link":"https://v.daum.net/v/20221203220007824","retrieved":1670073304534},{"title":"어둠 속에서 진실을 읽는 자는 누구인가","contents":"☞한겨레S 뉴스레터 무료 구독. 검색창에 ‘에스레터’를 쳐보세요. ※영화 &lt;올빼미&gt;의 줄거리가 상세히 서술되어 있습니다. 21세기 가장 사랑받는 장르 중 하나는 사극이다. &lt;명량&gt;(2014)이나 &lt;남한산성&gt;(2017) 같은 전통사극도 여전히 대중적이지만 &lt;광해&gt;(2012)나 &lt;관상&gt;(2013) 같은 퓨전사극이야말로 관객들을 사로잡는 매혹적인 이야기다. 퓨전","link":"https://v.daum.net/v/20221203193007013","retrieved":1670066097092},{"title":"'올빼미' 류준열 \"권력 없는 평범한 사람에게도 인간의 권리 있다는 메시지 담은 작품\"","contents":"영화 '올빼미'에서 세자의 죽음을 목격한 맹인 침술사 '경수'를 통해 배우로서 또 한번 연기 스펙트럼을 넓힌 류준열을 만났다. 극 중에서 '경수'는 뛰어난 침술 실력을 인정받은 맹인 침술사이지만 사실은 낮에는 앞이 보이지 않지만 빛이 없는 어두운 상황에서는 사물이 보이는 주맹증을 앓고 있는 인물로, 우연히 '소현세지'의 죽음을 목격하며 진실을 밝히기 위해","link":"https://v.daum.net/v/20221203192047960","retrieved":1670066097094},{"title":"②박진영 \"반삭에 실오라기 하나 걸쳤어도 행복했죠\"","contents":"[아시아경제 이이슬 기자] 훈훈한 유바비도, 달달한 아이돌도 없다. 배우 박진영(29)은 눈빛부터 달라졌다. 영화 '크리스마스 캐럴'에서 동생의 복수를 위해 소년원에 들어간 형제를 1인2역으로 소화하며 몸 사리지 않는 강렬한 액션을 펼친다. 잔혹한 싸움을 하며 거친 욕설도 거침없이 내뱉는다. 우리가 알던 얼굴은 어디에도 없다. 그야말로 강렬한 변신이다.","link":"https://v.daum.net/v/20221203184832780","retrieved":1670062006301},{"title":"'올빼미' 류준열 \"100대 명산 처럼 류준열 영화 100선 채우는게 꿈\"","contents":"영화 '올빼미'에서 세자의 죽음을 목격한 맹인 침술사 '경수'를 통해 배우로서 또 한 번 연기 스펙트럼을 넓힌 류준열을 만났다. 극 중에서 '경수'는 뛰어난 침술 실력을 인정받은 맹인 침술 사이지만 사실은 낮에는 앞이 보이지 않지만 빛이 없는 어두운 상황에서는 사물이 보이는 주맹증을 앓고 있는 인물로, 우연히 '소현세자'의 죽음을 목격하며 진실을 밝히기 위","link":"https://v.daum.net/v/20221203170745047","retrieved":1670055322305},{"title":"갓세븐 박진영의 열정 \"휴가 반납하고 연기\"","contents":"두 마리 토끼를 잡는 일은 쉽지 않다. 그래서 배우 박진영은 선택과 집중을 했다. 그룹 갓세븐으로 활동하다 휴가를 받으면 연기에 도전했다. 쉼 대신 연기를 택했던 일에 대해 \"욕심을 채웠다\"고 표현한 박진영에게서는 연기를 향한 깊은 열정이 느껴졌다. 박진영은 지난 2일 서울 종로구 삼청동 한 카페에서 진행된 인터뷰를 통해 영화 '크리스마스 캐럴'에 대한 다","link":"https://v.daum.net/v/20221203153755222","retrieved":1670051182277},{"title":"염동헌, 투병 중 2일 별세...유작은 영화 '서울의 봄'","contents":"[스타뉴스 이경호 기자] 배우 고(故) 염동헌./사진=스타빌리지엔터테인먼트\"연기를 사랑하고 열정적이었던 염동헌\" 배우 염동헌이 세상을 떠났다. 3일 스타빌리지엔터테인먼트는 공식입장을 통해 \"배우 염동헌씨가 2022년 12월 2일 밤 11시 50분경 향년 55세의 나이로 별세하셨습니다\"고 밝혔다. 이와 함께 \"스타빌리지엔터테인먼트는 연기를 사랑하고 열","link":"https://v.daum.net/v/20221203133757944","retrieved":1670044290175},{"title":"'트랜스포머: 비스트의 서막' 내년 6월 개봉 확정..예고편 최초 공개","contents":"[OSEN=하수정 기자] 전 세계가 기다려온 로봇 군단의 화려한 귀환 '트랜스포머: 비스트의 서막'이 2023년 6월 개봉을 확정 짓고 1차 포스터와 예고편을 공개했다. 2007년 획기적인 캐릭터, 차원이 다른 액션과 볼거리로 전 세계 극장가를 강타하며 시리즈의 성공적인 신호탄을 쏘아 올린 데 이어 매 작품마다 세계적인 신드롬과 흥행 돌풍을 일으켰던 '","link":"https://v.daum.net/v/20221203112450081","retrieved":1670036830520},{"title":"극장서 배우 연기력보단 줄거리 보는 세대","contents":"올해 '외계+인'과 '비상선언'의 흥행 실패는 더 이상 배우들의 이름값에 작품이 기댈 수 없다는 걸 확인 시켜줬다. 하지만 흥행 실패가 배우들만의 탓으로도 돌릴 수 없다. 팬데믹 이후 진입장벽이 높아진 극장가는 회복이 쉽사리 이뤄지지 않고 있으며 콘텐츠 소비습관들도 바뀌고 있다. 영화 제작진이 OTT로 넘어가면서 영화와 드라마 시리즈 콘텐츠의 완성도 차이도","link":"https://v.daum.net/v/20221203110035881","retrieved":1670033238015},{"title":"봉준호 감독의 애니메이션 꿈","contents":"[곽명동의 씨네톡] 그것이 꿈이든, 연인이든 첫사랑의 추억은 날카롭다. 인생의 한 축을 뒤흔드는 사건이었을테니까. 누구에게나 “평생을 좌우할 한 순간”이 있다. 그 순간을 지나면 과거로 되돌아갈 수 없다. 새로운 세상이 펼쳐지고, 경험하지 못한 인생이 열린다. 누구는 가는 길에 힘든 일을 겪으며 포기하겠지만, 또 다른 누군가는 강을 건너고 산을 넘어 끝내","link":"https://v.daum.net/v/20221203094741140","retrieved":1670033238017},{"title":"'올빼미', 10일째 130만 돌파…주말 흥행 이어질까","contents":"(서울=뉴스1) 정유진 기자 = 영화 '올빼미'(감독 안태진)가 개봉 10일째 1위를 지킨 가운데, 누적 130만 관객을 동원했다. 3일 영화진흥위원회 영화관 입장권 통합 전산망예 따르면 '올빼미'는 지난 2일 하루 9만5857명을 동원해 박스오피스 1위를 차지했다. 누적관객수는 130만6405명. '올빼미'는 이로써 지난달 23일 개봉한 이후 10일","link":"https://v.daum.net/v/20221203092523950","retrieved":1670033238018},{"title":"\"어이가 없네~\" 유아인 빠지고, '베테랑2' 촬영 시작 外","contents":"[스타뉴스 김미화 기자] /사진='베테랑2' ○...류승완 감독의 영화 '베테랑'의 속편 영화 '베테랑2'가 12월 촬영에 들어간다.  '베테랑'의 속편 '베테랑2'는 더욱 노련해진 서도철 형사(황정민 분)와 베테랑 강력범죄수사대에 닥친 새로운 위기를 그린 범죄액션이다. '베테랑2 '는 전편 연출을 맡았던 류승완 감독이 다시 메가폰을 잡았으며 1편의 흥행","link":"https://v.daum.net/v/20221203090002620","retrieved":1670033238019},{"title":"샬라메의 매력으로 빚은 '카니발리즘 로맨스', 소수자의 고통 비추다","contents":"[서울경제] 배우 티모시 샬라메와 루카 구아다니노 감독이 2018년작 ‘콜 미 바이 유어 네임’ 이후 4년만에 ‘본즈 앤 올’로 다시 조우했다. 전작과 마찬가지로 기둥 줄거리는 사랑 이야기이며, 구다아니노 감독의 영상미도, 샬라메의 연기력과 매력도 여전하다. 하지만 영화는 카니발리즘(식인)이라는 파격적 소재를 지렛대 삼아 소수자들의 소외, 이들을 향한 차","link":"https://v.daum.net/v/20221203080044203","retrieved":1670022688289},{"title":"'올빼미' 주말 극장가 꽉 잡았다…누적 150만 '눈앞'","contents":"[스포츠한국 조은애 기자] 영화 '올빼미'가 적수 없는 흥행 파워를 과시하고 있다. 3일 영진위 통합전산망 집계에 따르면 '올빼미'는 전날&nbsp;9만5858명의 관객을 동원하며 박스오피스 1위를 차지했다. 누적 관객 수는&nbsp;130만6406명이다. 유해진, 류준열 주연의 '올빼미'는 밤에만 앞이 보이는 맹인 침술사가 세자의 죽음을 목격한 후 진실을 밝히기","link":"https://v.daum.net/v/20221203074016990","retrieved":1670022688290}]}