{"title":"다음영화 뉴스 ─ 인기","url":"https://movie.daum.net/contents/news?type=popular","favicon":"https://movie.daum.net/contents/favicon.ico","elements":[{"title":"'고양이들의 아파트', 도시 속 길고양이 일상 담았다","contents":"[OSEN=김보라 기자]&nbsp;아파트 생태계를 통해 생태, 동물권, 환경 등의 주제를 폭넓게 사유하는 고양이 이주 프로젝트 '고양이들의 아파트'가 정재은 감독이 밝힌 프로덕션 비하인드를 공개해 눈길을 모은다. '고양이들의 아파트'(감독 정재은, 제작 영화사 못, 배급 엣나인필름 메타플레이)는 고양이를 통해 보다 차별화된 접근과 주제의식으로 도시 생태 문제를","link":"https://movie.v.daum.net/v/20220325171455646","retrieved":1648202834109,"image":"https://img1.daumcdn.net/thumb/S732x228/?fname=https%3A%2F%2Ft1.daumcdn.net%2Fnews%2F202203%2F25%2Fpoctan%2F20220325171455180equq.jpg"},{"title":"9살 소년의 눈으로 본 종교갈등.. 이 영화의 진솔함","contents":"[원종빈 기자] ▲ &nbsp;영화 &lt;벨파스트&gt; 포스터    ⓒ 유니버설 픽쳐스  *주의! 이 기사에는 영화의 스포일러가 포함돼 있습니다. 1969년의 벨파스트. 날이 좋으면&nbsp;골목에서 함께 춤추며 놀고,&nbsp;해 질 녘엔 가족들이 다 함께 모여&nbsp;저녁을 먹으며, 거리의 모두가 서로의 가족을 알고 아끼며 지내던 도시. 어느 날, 종교를 이유로 폭력 사건과 격렬","link":"https://movie.v.daum.net/v/20220325145700502","retrieved":1648199288653,"image":"https://img1.daumcdn.net/thumb/S732x228/?fname=https%3A%2F%2Ft1.daumcdn.net%2Fnews%2F202203%2F25%2Fohmynews%2F20220325145701546ysmz.jpg"},{"title":"사진 유출범이 정의의 기사? 이해 못할 이 영화의 선택","contents":"[이선필 기자] ▲ &nbsp;영화 &lt; B컷 &gt; 관련 이미지.    ⓒ TCO(주)더콘텐츠온  대선 철을 기대한 노림수일까. 범죄 행위를 숨긴 국회의원과 진실을 파헤치려는 피해자 간의 대결을 그린 영화 &lt; B컷 &gt;이 지난 24일 언론에 선 공개됐다. 장르를 따지자면 스릴러에 가깝다고 할 수 있다. 대권을 노리는 유력 정치인(김병옥)이 사실은 아내를 학","link":"https://movie.v.daum.net/v/20220325163304292","retrieved":1648199288666,"image":"https://img1.daumcdn.net/thumb/S384x240/?fname=https%3A%2F%2Ft1.daumcdn.net%2Fnews%2F202203%2F25%2Fohmynews%2F20220325163305369jrfl.jpg"},{"title":"'오징어게임' 성공, \"전세계인이 영어·미국·백인 이외의 콘텐츠에 열광하는 증거\"[해외이슈]","contents":"[마이데일리 = 곽명동 기자]최근 스티븐 스필버그 감독이 ‘오징어게임’ 주연배우들이 ‘알 수 없는 사람들’이라고 지칭한 이후 미국 중심주의 시각을 버려야한다는 주장이 제기되고 있다. 최근 스티븐 스필버그 감독은 미국 제작자조합 시상식에서 할리우드의 스타 파워에 대한 의존도와 최근 넷플릭스 쇼가 업계에 가져온 변화에 대해 말했다. 그는 “‘오징어 게임’은","link":"https://movie.v.daum.net/v/20220326191020186","retrieved":1648292765677,"image":"https://img1.daumcdn.net/thumb/S384x240/?fname=https%3A%2F%2Ft1.daumcdn.net%2Fnews%2F202203%2F26%2Fmydaily%2F20220326191021049qskv.jpg"},{"title":"[더보기] '모비우스'부터 '신비한 동물'까지..처참한 극장가 펜데믹 종식시킬까","contents":"박스오피스 1위 영화의 일일 관객 수가 만 명을 넘지 못했다. 코로나19 여파로 관객 수가 줄었다고 하지만 심각한 수준이다. 그러나 개봉을 미뤘던 할리우드 대작들이 잇따라 나올 준비를 마쳤다. 마블 히어로물부터 코미디 어드벤처물, 시리즈 판타지물, 액션 블록버스터까지 다채로운 대작들이 극장가에 단비가 될 수 있을지 주목된다. #상상력을 자극하는 힘 ‘","link":"https://movie.v.daum.net/v/20220325083133020","retrieved":1648168063402,"image":"https://img1.daumcdn.net/thumb/S384x240/?fname=https%3A%2F%2Ft1.daumcdn.net%2Fnews%2F202203%2F25%2Filgansports%2F20220325083135036ebyb.jpg"},{"title":"고마츠 나나 주연 '달빛 그림자' 4월 27일 개봉 확정","contents":"[동아닷컴] 고마츠 나나 주연 ‘달빛 그림자’ 4월 27일 개봉 확정 고마츠 나나 주연의 가슴 저미는 러브 스토리 ‘달빛 그림자’가 4월 27일 개봉을 확정하며, 애틋한 감동을 예고하는 메인 포스터를 공개했다. 2022년 4월 27일 국내개봉을 확정한 ‘달빛 그림자’가 관객들의 감성을 자극하는 메인 포스터를 공개했다. 영화 ‘달빛 그림자’는 어느날 갑자기","link":"https://movie.v.daum.net/v/20220325092612479","retrieved":1648181365058,"image":"https://img1.daumcdn.net/thumb/S384x240/?fname=https%3A%2F%2Ft1.daumcdn.net%2Fnews%2F202203%2F25%2Fsportsdonga%2F20220325092614917aalr.jpg"},{"title":"세월 뛰어넘은 수사 공조, 일본 버전 '시그널'의 매력","contents":"[김준모 기자] &nbsp;        ▲ &nbsp;&lt;극장판 시그널&gt; 포스터    ⓒ (주)미디어캐슬   &nbsp; 2016년 tvN을 통해 방영된 드라마 &lt;시그널&gt;은 올해의 드라마라 불릴 만큼 선풍적인 인기를 끌은 작품입니다. &lt;싸인&gt; &lt;유령&gt;을 통해 국내 드라마계에 장르물을 정착시킨 김은희 작가의 대표작이라 할 수 있는 이 드라마는 2018년 일본에서 리메이크가 되어 후지T","link":"https://movie.v.daum.net/v/20220325145100365","retrieved":1648199288656,"image":"https://img1.daumcdn.net/thumb/S384x240/?fname=https%3A%2F%2Ft1.daumcdn.net%2Fnews%2F202203%2F25%2Fohmynews%2F20220325145101446clhw.jpg"},{"title":"'뜨거운 피' 정우의 성장통 [인터뷰]","contents":"[스포츠투데이 최혜진 기자] 성장통은 점점 자라며 생기는 고통을 뜻한다. 배우 정우의 연기가 이러한 성장통을 겪었다. 크고 깊어지는 감정 연기를 표현함에 따라 큰 고통과 무게를 감내해야 했다. 그러나 그 결과는 값지다. 한층 성숙해진 모습으로 관객들 앞에 선 정우다. 정우는 2001년 영화 '7인의 새벽'으로 데뷔해 '바람' '스페어' '이웃사촌', 드라","link":"https://movie.v.daum.net/v/20220325143232836","retrieved":1648199288674,"image":"https://img1.daumcdn.net/thumb/S384x240/?fname=https%3A%2F%2Ft1.daumcdn.net%2Fnews%2F202203%2F25%2Fsportstoday%2F20220325143233532xncv.jpg"},{"title":"'배우 출신' 우크라이나 대통령, 아카데미 시상식 출연 협의 중[Oh!llywood]","contents":"[OSEN=최나영 기자] 볼로디미르 젤렌스키 우크라이나 대통령이 제 94회 아카데미 시상식에&nbsp;출연하는 것을 두고 주최 측과 협의 중이라고 뉴욕포스트가 25일(현지시간) 전했다. 아카데미 시상식 관계자들에 따르면 그가&nbsp;생방송으로 등장할 지 아니면 촬영된 영상물로&nbsp;나타날지, 그 구체적인 출연 형태는 확실치 않다.&nbsp; 또 소식통에 따르면&nbsp;러시아의 우크라이나 침","link":"https://movie.v.daum.net/v/20220326162716952","retrieved":1648282025905,"image":"https://img1.daumcdn.net/thumb/S384x240/?fname=https%3A%2F%2Ft1.daumcdn.net%2Fnews%2F202203%2F26%2Fpoctan%2F20220326162717448kvfw.jpg"},{"title":"'파친코' 진하, 韓 할머니 불법 촬영·성희롱 사과 \"과거 내 행동 후회\"[전문]","contents":"[스타뉴스 김나연 기자] 배우 진하가 18일 오전 온라인으로 진행된 드라마 '파치코' 인터뷰에 앞서 포즈를 취하고 있다. 2022.03.18 &lt;사진=애플TV플러스&gt; /사진=임성균 기자 tjdrbs23@한국계 미국인 배우 진하의 과거 불법 촬영 및 성희롱 발언이 논란의 중심에 선 가운데, 그가 해당 SNS를 삭제하고 사과했다. 26일 진하는 자신의 홈페이","link":"https://movie.v.daum.net/v/20220326154814452","retrieved":1648278338818,"image":"https://img1.daumcdn.net/thumb/S384x240/?fname=https%3A%2F%2Ft1.daumcdn.net%2Fnews%2F202203%2F26%2Fstarnews%2F20220326161635039qfvy.jpg"},{"title":"베네딕트 컴버배치의 '루이스 웨인:사랑을 그린 고양이 화가' 스페셜 도슨트 영상 공개","contents":"[동아닷컴]  베네딕트 컴버배치의 ‘루이스 웨인:사랑을 그린 고양이 화가’ 스페셜 도슨트 영상 공개 배우 베네딕트 컴버배치가 선사할 올봄, 놀랍도록 다정한 로맨스 영화 &lt;루이스 웨인: 사랑을 그린 고양이 화가&gt;가 화가 ‘루이스 웨인’에 대한 궁금증을 해결해 줄 ‘스페셜 도슨트 영상’을 전격 공개했다. (원제: The Electrical Life of Lo","link":"https://movie.v.daum.net/v/20220325085836566","retrieved":1648174506179,"image":"https://img1.daumcdn.net/thumb/S384x240/?fname=https%3A%2F%2Ft1.daumcdn.net%2Fnews%2F202203%2F25%2Fsportsdonga%2F20220325085837856qlvv.jpg"},{"title":"13년 콜트콜텍 투쟁.. '언니'라 불린 이 남자","contents":"[이선필 기자] ▲ &nbsp;다큐멘터리 영화 &lt;재춘 언니&gt; 관련 사진.    ⓒ 시네마달  \"정권이 바뀌어도 노동자 문제는 늘 변하지 않았습니다. 사람들이 자기 일이라고 생각하지 않기 때문입니다. 우리 땐 부당해고, 요즘은 비정규직 싸움입니다. 자식과 조카, 가족을 위해서라도 싸워야 합니다. 부딪히면 언젠가는 들어준다고 믿습니다.\" (임재춘씨) 콜트","link":"https://movie.v.daum.net/v/20220325115100087","retrieved":1648184762159,"image":"https://img1.daumcdn.net/thumb/S384x240/?fname=https%3A%2F%2Ft1.daumcdn.net%2Fnews%2F202203%2F25%2Fohmynews%2F20220325115100482favn.jpg"},{"title":"'모가디슈'·'신과 함께' 방준석 음악감독, 위암으로 별세..향년 52세[종합]","contents":"[OSEN=김보라 기자]&nbsp;방준석 음악감독이 세상을 떠났다. 향년 52세. 26일 유족 측에 따르면 방 음악감독은 이날 오전 7시 사망했다. 사인은 위암. 위암 치료를 받아왔던 그가 완치 판정을 받았으나, 재발해 2년여 전부터 다시 투병 생활을 해왔다는 설명이다. 삼성서울병원 장례식장에 빈소가 마련됐으며, 28일 오후 3시 30분 발인을 진행한다. 장지는","link":"https://movie.v.daum.net/v/20220326151121065","retrieved":1648278338847,"image":"https://img1.daumcdn.net/thumb/S384x240/?fname=https%3A%2F%2Ft1.daumcdn.net%2Fnews%2F202203%2F26%2Fpoctan%2F20220326151122873vooo.jpg"},{"title":"'스타' 이민호도, '신예' 김민하도..성장의 '파친코' [★FULL인터뷰]","contents":"[스타뉴스 김나연 기자] 이민호 김민하 / 사진=애플TV플러스주연 작품을 셀 수 없는 13년 차 배우 이민호도, 첫 주연으로 데뷔하는 6년 차 배우 김민하도 예외는 없었다. '파친코'를 통해 한 단계 성장한 두 사람이다. 최근 애플TV+ '파친코' - Pachinko의 배우 윤여정, 진하의 공통 인터뷰가 온라인으로 진행됐다. '파친코'는 동명의 뉴욕타임","link":"https://movie.v.daum.net/v/20220326133000031","retrieved":1648271172966,"image":"https://img1.daumcdn.net/thumb/S384x240/?fname=https%3A%2F%2Ft1.daumcdn.net%2Fnews%2F202203%2F26%2Fstarnews%2F20220326133003577hfca.jpg"},{"title":"\"아름다운 사람이 떠났다\" 방준석 음악감독 별세..이준익·윤종신 등 추모 물결[종합]","contents":"[마이데일리 = 곽명동 기자]음악감독 겸 프로듀서 방준석이 세상을 떠났다. 향년 52세. 26일 영화계에 따르면 방준석 감독은 이날 오전 7시께 병환으로 별세했다. 고인은 위암으로 투병해온 것으로 알려졌다. 고인은 2018년 한 시사지와 인터뷰에서 “6년 전쯤 좀 고약한 형태의 위암에 걸렸다”면서 “수술과 항암 치료 등을 거부하고 자연치유법을 택했다.","link":"https://movie.v.daum.net/v/20220326211640004","retrieved":1648300507952,"image":"https://img1.daumcdn.net/thumb/S384x240/?fname=https%3A%2F%2Ft1.daumcdn.net%2Fnews%2F202203%2F26%2Fmydaily%2F20220326211640628xfyz.jpg"},{"title":"\"충무로 인재 잃었다\"..방준석 음악감독 별세 [이슈&톡]","contents":"[티브이데일리 이기은 기자] 충무로의 없어서는 안 될 현역이 모두의 곁을 떠났다. 영화 '자산어보' '모가디슈' 등 유명 영화 음악 감독 방준석 씨가 세상을 떴다는 소식에 관계자들과 대중들의 안타까움이 커진다. 26일 영화계에 따르면 방준석 음악 감독은 이날 오전 7시께 지병으로 사망했다. 향년 52세. 고인은 1970년생으로 앞서 1994년 그룹 유앤비","link":"https://movie.v.daum.net/v/20220326153715356","retrieved":1648278338829,"image":"https://img1.daumcdn.net/thumb/S384x240/?fname=https%3A%2F%2Ft1.daumcdn.net%2Fnews%2F202203%2F26%2Ftvdaily%2F20220326153716442qnrp.jpg"},{"title":"'몰카' 진하, 이틀째 묵묵부답..윤여정·이민호 얼굴 보기 안 부끄럽나?(종합)[Oh!쎈 초점]","contents":"[OSEN=김보라 기자]&nbsp;한국계 미국인 배우 진하가 11~12년 전 국내에서 노인 여성들의 사진을 동의없이 무단 촬영하고 게재했던 것으로 드러났다. 애플TV+ 드라마 ‘파친코’가 공개된 지난 25일 이 같은 소식이 전해졌는데 당일은 물론 하루가 지난 오늘(26일)까지도 묵묵부답으로 일관하고 있다. 진하가 개인 인스타그램 및 트위터, 블로그를 활발하게 운","link":"https://movie.v.daum.net/v/20220326104412653","retrieved":1648264550161,"image":"https://img1.daumcdn.net/thumb/S384x240/?fname=https%3A%2F%2Ft1.daumcdn.net%2Fnews%2F202203%2F26%2Fpoctan%2F20220326104412327nubr.jpg"},{"title":"김우빈, '♥신민아 남친'에 가려진 본모습..지질한 양다리에 욕설까지 [TEN스타필드]","contents":"[텐아시아=태유나 기자] 《태유나의 넷추리》 태유나 텐아시아 기자가 수많은 콘텐츠로 가득한 넷플릭스 속 알맹이만 골라드립니다. 매주 금요일 저녁 꼭 봐야 할 '띵작'부터 기대되는 신작까지 주말에 방구석 1열에서 즐길 수 있는 작품들을 추천하겠습니다.배우 김우빈이 tvN 예능 '어쩌다 사장 2'를 통한 복귀 신고식을 마친다. 비인두암 투병 끝에 내달 방송","link":"https://movie.v.daum.net/v/20220325155802782","retrieved":1648195825333,"image":"https://img1.daumcdn.net/thumb/S384x240/?fname=https%3A%2F%2Ft1.daumcdn.net%2Fnews%2F202203%2F25%2F10asia%2F20220325155804990rbyf.jpg"},{"title":"영화 음악감독 방준석, 위암으로 별세..'신과 함께' 등 작업","contents":"(서울=연합뉴스) 오보람 기자 = 밴드 유앤미블루 출신 영화 음악감독 방준석 씨가 52세를 일기로 세상을 떠났다. 26일 유족에 따르면 방 감독은 이날 오전 7시 위암으로 별세했다. 몇 년 전 위암 치료를 받은 그는 이후 완치 판정을 받았으나 2020년 가을 재발해 투병을 이어왔다. 미국에서 살던 고인은 스물네 살이던 1994년 이승열과 함께 유앤미블루를","link":"https://movie.v.daum.net/v/20220326135350300","retrieved":1648274889945,"image":"https://img1.daumcdn.net/thumb/S384x240/?fname=https%3A%2F%2Ft1.daumcdn.net%2Fnews%2F202203%2F26%2Fyonhap%2F20220326135350563ljbt.jpg"},{"title":"예외는 없다..윤여정·이민호·김민하, 치열했던 '파친코' 오디션 [김나연의 사선]","contents":"[스타뉴스 김나연 기자] 영화·OTT를 보는 김나연 기자의 '사적인 시선' 파친코 / 사진=애플TV플러스치열했다. 제작비만 무려 1000억, 엄청난 스케일을 자랑하는 만큼 그 '주역'을 찾기란 쉬운 일이 아니었다. 애플 TV+ '파친코'의 이야기다. Apple Original Series 최고 기대작 '파친코' - Pachinko(이하 '파친코')는","link":"https://movie.v.daum.net/v/20220326113901203","retrieved":1648310817898,"image":"https://img1.daumcdn.net/thumb/S384x240/?fname=https%3A%2F%2Ft1.daumcdn.net%2Fnews%2F202203%2F26%2Fstarnews%2F20220326113902659xcyc.jpg"}]}