{"title":"다음 연예 ─ 뉴스 ─ 예능","url":"https://entertain.daum.net/news/variety","favicon":"https://entertain.daum.net/news/favicon.ico","elements":[{"title":"'108kg' 강재준, 벌써 10kg 감량…\"지금부터가 필사적\"","contents":"(엑스포츠뉴스 오승현 기자) 개그맨 강재준이 다이어트 근황을 전했다. 27일 오후 개그맨 강재준과 이은형 부부의 유튜브 채널 '기유TV'에는 '※강재준의 다이어트※ 2주차 : 2주만에 과연 몇 kg?'라는 제목의 영상이 올라왔다. 이날 강재준은 아침에 공복 유산소 운동을 했음에도 이은형과 백화점 데이트를 위해 집에서 백화점까지 걸어가며 또 운동을 했다. 강","link":"https://v.daum.net/v/20230127171805572","retrieved":1674807643817},{"title":"홍성흔, 딸 이어 아들과도 불화‥“숨 막혀서 못 산다”","contents":"[뉴스엔 배효주 기자] 홍성흔이 아들과의 갈등을 폭발시킨다. 1월 28일 KBS 2TV '살림하는 남자들 시즌2'에서는 연초부터 아들 화철과 사이가 멀어진 홍성흔의 고민이 그려진다. 최근 홍성흔은 운동복, 글러브 등을 집에 놓고 가기 일쑤에, 짐이 많다며 데리러 와달라고 응석을 부리는 등 부모에게 의존적인 화철을 탐탁치 않아 했다. 아들을 더 강하게 키워","link":"https://v.daum.net/v/20230127171336456","retrieved":1674807643826},{"title":"이은결 “1분 마술에 2억 태워” 제작비 합치면 빌딩 수준","contents":"[뉴스엔 배효주 기자] 이은결이 \"1분에 2억을 태웠다\"고 말해 모두를 놀라게 한다. 1월 29일 방송되는 KBS 2TV 예능 '사장님 귀는 당나귀 귀'에서는 이은결의 27년 내공과 노하우가 집약된 마술쇼 비하인드가 공개된다. 이은결은 헬기를 타고 깜짝 등장하는가 하면 불타는 예리한 못을 상자에 꽂아 넣는 등 화려하고도 아찔한 퍼포먼스 영상으로 시작부터","link":"https://v.daum.net/v/20230127170923326","retrieved":1674807643828},{"title":"마술사 이은결 \"1분 위해 2억원 썼다\"","contents":"[스타뉴스 김노을 기자] /사진=KBS'당나귀 귀' 마술사 이은결이 억소리나는 매직 플렉스를 공개한다. 오는 29일 방송되는 KBS 2TV 예능프로그램 '사장님 귀는 당나귀 귀'에서는 이은결의 27년 내공과 노하우가 집약된 마술쇼 비하인드가 공개된다. 앞서 진행된 녹화에서 이은결은 헬기를 타고 깜짝 등장하는가 하면 불타는 예리한 못을 상자에 꽂아 넣는","link":"https://v.daum.net/v/20230127170901317","retrieved":1674807643829},{"title":"하정우 “母가 기도한 듯” 신들린 복불복으로 영웅 등극","contents":"[뉴스엔 이하나 기자] 하정우가 기막힌 뽑기 운으로 첫날 용돈의 한을 풀었다. 1월 27일 공개된 티빙 오리지널 ‘두발로 티켓팅’에서는 하정우, 주지훈, 최민호, 여진구의 뉴질랜드 여행 둘째 날 모습이 공개 됐다. 네 사람은 매일 아침 게임을 통해 하루 용돈을 획득했다. 첫째날 겨우 26달러를 받아 감자로 허기를 때웠던 하정우는 “빨리 하자. 너무 불","link":"https://v.daum.net/v/20230127165255887","retrieved":1674807643830},{"title":"큰형님 된 ‘나꼰대’ 나인우, 서열자리 1위 고수?","contents":"[OSEN=강서정 기자] 큰형님이 된 ‘나꼰대’ 나인우가 서열 1위 자리를 고수할 수 있을까. 오는 29일 방송되는 KBS 2TV ‘1박 2일 시즌4’(이하 ‘1박 2일’) ‘나이는 떡국 숫자에 불과하다’ 특집에서는 여섯 남자의 달콤하고도 씁쓸한 대결이 그려진다.&nbsp; 지난주 ‘내 분신을 지켜라’ 미션에서 승리해 1세가 된 나인우는 0세인 멤버들을 쥐락펴락","link":"https://v.daum.net/v/20230127165236876","retrieved":1674807643832},{"title":"김정현, 5년 전 '태도 논란' 언급 \"기억 없어 낯설다\"","contents":"(엑스포츠뉴스 이예진 기자) 배우 김정현이 태도 논란과 사생활 논란 이후 2년만에 복귀하며 소감을 전했다. 27일 서울 마포구 상암 MBC 골든마우스홀에서 MBC 새 금토드라마 '꼭두의 계절' 제작발표회가 진행됐다. 이 자리에는 김정현, 임수향, 김다솜, 안우연, 김인권, 차청화, 백수찬 감독이 참석했다. '꼭두의 계절'은 99년마다 인간에게 천벌을 내리러","link":"https://v.daum.net/v/20230127165008816","retrieved":1674807643833},{"title":"정보석x이장우 대신 박상원x오민석 투입..'운탄고도 마을호텔2' 커밍순","contents":"[OSEN=박소영 기자] tvN STORY ‘운탄고도 마을호텔’이 시즌&nbsp;2&nbsp;방영을 확정했다.&nbsp;정보석-이장우 대신 박상원-오민석이 투입된다. 오는&nbsp;2월&nbsp;24일(금)&nbsp;저녁&nbsp;8시&nbsp;20분 첫 방송 예정인&nbsp;‘운탄고도 마을호텔&nbsp;2’는 국내에서 가장 아름다운 겨울을 만날 수 있는 태백에서 새롭게 마을 호텔을 운영하면서 벌어지는 일들을 그리는 리얼 관찰 예능이다. 특","link":"https://v.daum.net/v/20230127164910788","retrieved":1674807643834},{"title":"‘운탄고도 마을호텔2’ 엄홍길 인맥으로 박상원X오민석 합류","contents":"[뉴스엔 배효주 기자] '운탄고도 마을호텔' 시즌 2에 박상원, 오민석이 합류한다. 2월 24일 오후 8시 20분 첫 방송되는 tvN STORY '운탄고도 마을호텔 2'에는 엄홍길의 인맥으로 박상원, 오민석이 합류한다. 박상원은 엄홍길과 15년 우정으로도 유명할 뿐만 아니라 전문 산악인 못지 않게 히말라야의 산맥인 안나푸르나, 에베레스트, 마칼루 등 등","link":"https://v.daum.net/v/20230127164812763","retrieved":1674807643839},{"title":"‘당나귀 귀’ 이은결, 1mm 오차도 허용 못해‥전현무 “병원에 가”","contents":"[뉴스엔 배효주 기자] '당나귀 귀'에 이은결이 새로운 보스로 출연한다. 1월 29일 방송되는 KBS 2TV 예능 ‘사장님 귀는 당나귀 귀’에는 국가대표 일루셔니스트 이은결과 걸그룹 비비지의 은하가 각각 새로운 보스와 스페셜 MC로 출연한다. 새로운 보스로 합류한 이은결은 눈을 사로잡는 화려한 퍼포먼스로 관객들에게 웃음과 희망을 주는 27년 차 일루셔니스","link":"https://v.daum.net/v/20230127164346642","retrieved":1674807643839},{"title":"진태현♥︎박시은, 아이 떠나 보낸 후 근황..“사실 계속 참고 있는 것” 고백","contents":"[OSEN=김채연 기자] 배우 이윤지, 진태현♥︎박시은 부부가&nbsp;SBS ‘동상이몽2&nbsp;-&nbsp;너는 내 운명’(이하&nbsp;‘동상이몽2’)에 오랜만에 반가운 얼굴을 드러낸다. 오는 30일&nbsp;방송되는&nbsp;SBS ‘동상이몽2’에는 배우 이윤지가 스페셜&nbsp;MC로 출연한다.&nbsp;이윤지는 과거&nbsp;‘동상이몽’을 통해 남편 정한울과 애교 넘치는 딸 라니와의 행복한 일상은 물론 둘째 소울이를 최초","link":"https://v.daum.net/v/20230127164120570","retrieved":1674807643840},{"title":"김재우, 사랑꾼 비결은 “♥조유리 ‘예쁜아’ 라고 불러”","contents":"[뉴스엔 배효주 기자] '어쩌다 어른' 김재우가 사랑꾼이 된 비결을 밝힌다. 1월 31일 오후 8시 20분 방송되는 tvN STORY ‘어쩌다 어른’에 이재용, 박은영, 김재우, 초아가 게스트로 출격한다. 이날 방송에서 김재우는 학창 시절 아버지의 말 한마디로 인해 지금의 개그맨이 될 수 있었던 사연, 박은영의 아나운서 합격 비결 중 가장 결정적이었던 것","link":"https://v.daum.net/v/20230127163013226","retrieved":1674807643841},{"title":"민호X유세윤X장도연 ‘웹툰싱어’ K-웹툰과 K-팝 만남이라니","contents":"[뉴스엔 박아름 기자] '웹툰싱어'가 새로운 K-콘텐츠의 탄생을 알렸다. 티빙 오리지널 '웹툰싱어' 측은 1월 27일 메인 예고를 공개했다. MC 샤이니 민호의 내레이션으로 시작되는 영상은 세계 최초 대한민국에서 시작된 K-웹툰과 글로벌을 사로잡은 K-팝의 만남을 화려하게 제시한다. K-팝 아티스트가 시공간의 경계를 허물어 웹툰 속 주인공이 된 듯 차원","link":"https://v.daum.net/v/20230127162632088","retrieved":1674807643841},{"title":"“처음 몸무게 60kg대 찍어”..조권, 먹방 후 체중 앞자리 바뀌고 ‘감격’","contents":"[OSEN=강서정 기자] ‘돈쭐내러 왔습니다' 먹요원이 목표 먹방을 달성하며 사장님과의 첫 대결에서 승리를 거머쥐었다. 지난 26일 방송된 채널 IHQ 예능 프로그램 '돈쭐내러 왔습니다' 71회에서는 서울시 강서구 화곡동에 위치한 한 전복 소갈비찜 맛집 사장님과 맞대결을 펼치는 먹피아 조직의 모습이 전파를 탔다. 이날 이영자, 제이쓴은 \"기존에는 먹요원","link":"https://v.daum.net/v/20230127162613080","retrieved":1674807643842},{"title":"억대 유튜버 ‘신사임당’ 주언규, 채널 20억원 매각 후 “재산은..”","contents":"[OSEN=강서정 기자] 유튜브 채널 신사임당으로 유명한 주언규PD가 자신의 재산과 부자가 되고 싶었던 이유를 밝혔다.&nbsp;&nbsp; 지난 26일 공개된&nbsp;IHQ&nbsp;바바요 ‘뻥쿠르트’에서는 방송국&nbsp;PD에서 유튜브 크리에이터로 변신 후 성공 사업의 아이콘으로 자리 잡은 주언규가 출연헸다.&nbsp;&nbsp; ‘뻥쿠르트’는 동네 구석구석을 누비며 시민들을 만나고,&nbsp;화제의 중심에 선 게스","link":"https://v.daum.net/v/20230127162218965","retrieved":1674807643843}]}